pulumi_opnsense/__init__.py
pulumi_opnsense/_utilities.py
pulumi_opnsense/provider.py
pulumi_opnsense/pulumi-plugin.json
pulumi_opnsense/py.typed
pulumi_opnsense/config/__init__.py
pulumi_opnsense/config/__init__.pyi
pulumi_opnsense/config/vars.py
pulumi_opnsense/unbound/__init__.py
pulumi_opnsense/unbound/host_alias_override.py
pulumi_opnsense/unbound/host_override.py
pulumi_opnsense-0.3.45.dist-info/METADATA
pulumi_opnsense-0.3.45.dist-info/WHEEL
pulumi_opnsense-0.3.45.dist-info/top_level.txt
pulumi_opnsense-0.3.45.dist-info/RECORD
