Metadata-Version: 2.2
Name: pulumi_opnsense
Version: 0.3.45
Summary: The Pulumi OpnSense provider is used to interact with the resources supported by OpnSense.
License: Apache-2.0
Project-URL: Homepage, https://github.com/oss4u/pulumi-opnsense
Project-URL: Repository, https://github.com/oss4u/pulumi-opnsense
Keywords: pulumi,opnsense
Requires-Python: >=3.8
Requires-Dist: parver>=0.2.1
Requires-Dist: pulumi<4.0.0,>=3.0.0
Requires-Dist: semver>=2.8.1
Requires-Dist: typing-extensions>=4.11; python_version < "3.11"
